[
    {
        "Party": "राष्ट्रिय स्वतन्त्र पार्टी",
        "Votes": 1461381
    },
    {
        "Party": "नेपाली काँग्रेस",
        "Votes": 494251
    },
    {
        "Party": "नेपाल कम्युनिष्ट पार्टी (एकीकृत मार्क्सवादी लेनिनवादी)",
        "Votes": 403899
    },
    {
        "Party": "नेपाली कम्युनिष्ट पार्टी",
        "Votes": 193550
    },
    {
        "Party": "राष्ट्रिय प्रजातन्त्र पार्टी",
        "Votes": 106396
    },
    {
        "Party": "श्रम संस्कृति पार्टी",
        "Votes": 59241
    },
    {
        "Party": "राष्ट्रिय परिवर्तन पार्टी",
        "Votes": 36863
    },
    {
        "Party": "जनता समाजवादी पार्टी, नेपाल",
        "Votes": 27304
    },
    {
        "Party": "जनमत पार्टी",
        "Votes": 14250
    },
    {
        "Party": "नेपाल मजदुर किसान पार्टी",
        "Votes": 12983
    },
    {
        "Party": "एकल चिन्ह चकिया (जाँतो) (राष्ट्रिय मुक्ति पार्टी नेपाल/जनता समाजवादी पार्टी/नागरिक उन्मुक्ति पार्टी, नेपाल)",
        "Votes": 12852
    },
    {
        "Party": "राष्ट्रिय जनमोर्चा",
        "Votes": 9997
    },
    {
        "Party": "नेपाल कम्युनिस्ट पार्टी (माओवादी)",
        "Votes": 9913
    },
    {
        "Party": "राष्ट्र निर्माण दल नेपाल",
        "Votes": 9215
    },
    {
        "Party": "नेपाल जनता संरक्षण पार्टी",
        "Votes": 6873
    },
    {
        "Party": "प्रगतिशील लोकतान्त्रिक पार्टी",
        "Votes": 5157
    },
    {
        "Party": "मंगोल नेशनल अर्गनाइजेशन",
        "Votes": 4330
    },
    {
        "Party": "सार्वभौम नागरिक पार्टी",
        "Votes": 3852
    },
    {
        "Party": "एकल चिन्ह  बस (नेपाल संघीय समाजवादी पार्टी/बहुजन एकता पार्टी नेपाल/नेपाल जनजागृति पार्टी)",
        "Votes": 3181
    },
    {
        "Party": "राष्ट्रिय मुक्ति आन्दोलन, नेपाल",
        "Votes": 3094
    },
    {
        "Party": "एकल चिन्ह मोबाइल (आम जनता पार्टी/जनादेश पार्टी नेपाल)",
        "Votes": 2357
    },
    {
        "Party": "संयुक्त नागरिक पार्टी",
        "Votes": 2252
    },
    {
        "Party": "नेपाल जनता पार्टी",
        "Votes": 2119
    },
    {
        "Party": "नेशनल रिपब्लिक नेपाल",
        "Votes": 1903
    },
    {
        "Party": "राष्ट्रिय एकता दल",
        "Votes": 1866
    },
    {
        "Party": "राष्ट्रिय जनमुक्ति पार्टी",
        "Votes": 1641
    },
    {
        "Party": "नेपाल कम्युनिष्ट पार्टी (मार्क्सवादी-लेनिनवादी)",
        "Votes": 1447
    },
    {
        "Party": "नेपाल कम्युनिष्ट पार्टी मार्क्सवादी (पुष्पलाल)",
        "Votes": 1375
    },
    {
        "Party": "नेपाल कम्युनिष्ट पार्टी (संयुक्त)",
        "Votes": 1154
    },
    {
        "Party": "नेपाल मातृभूमि पार्टी",
        "Votes": 1087
    },
    {
        "Party": "राष्ट्रिय गौरव पार्टी",
        "Votes": 1082
    },
    {
        "Party": "नेपालका लागि नेपाली पार्टी",
        "Votes": 1040
    },
    {
        "Party": "समावेशी समाजवादी पार्टी नेपाल",
        "Votes": 983
    },
    {
        "Party": "नेपाल लोकतान्त्रिक पार्टी",
        "Votes": 944
    },
    {
        "Party": "गतिशील लोकतान्त्रिक पार्टी",
        "Votes": 920
    },
    {
        "Party": "संघीय लोकतान्त्रिक राष्ट्रिय मञ्च",
        "Votes": 916
    },
    {
        "Party": "जय मातृभूमि पार्टी",
        "Votes": 830
    },
    {
        "Party": "राष्ट्रिय जनता पार्टी नेपाल",
        "Votes": 699
    },
    {
        "Party": "बहुजन शक्ति पार्टी",
        "Votes": 595
    },
    {
        "Party": "राष्ट्रिय उर्जाशील पार्टी, नेपाल",
        "Votes": 582
    },
    {
        "Party": "पिपुल फर्ष्ट पार्टी",
        "Votes": 550
    },
    {
        "Party": "नेपाल जनमुक्ति पार्टी",
        "Votes": 547
    },
    {
        "Party": "प्रजातान्त्रिक पार्टी नेपाल",
        "Votes": 519
    },
    {
        "Party": "नागरिक शक्ति, नेपाल",
        "Votes": 454
    },
    {
        "Party": "नेपाली काँग्रेस (वी.पी.)",
        "Votes": 451
    },
    {
        "Party": "जन अधिकार पार्टी",
        "Votes": 443
    },
    {
        "Party": "नेपाल सद्‍भावना पार्टी",
        "Votes": 439
    },
    {
        "Party": "जनता लोकतान्त्रिक पार्टी, नेपाल",
        "Votes": 415
    },
    {
        "Party": "समावेशी समाजवादी पार्टी",
        "Votes": 398
    },
    {
        "Party": "नेपाली जनता दल",
        "Votes": 357
    },
    {
        "Party": "नेपाली जनश्रमदान संस्कृति पार्टी",
        "Votes": 345
    },
    {
        "Party": "स्वाभिमान पार्टी",
        "Votes": 321
    },
    {
        "Party": "एकल चिन्ह जगर भएको सिंह(सचेत नेपाली पार्टी/नागरिक सर्वोच्चता पार्टी नेपाल)",
        "Votes": 257
    },
    {
        "Party": "मितेरी पार्टी नेपाल",
        "Votes": 225
    },
    {
        "Party": "जनप्रिय लोकतान्त्रिक पार्टी",
        "Votes": 207
    },
    {
        "Party": "त्रिमुल नेपाल",
        "Votes": 191
    },
    {
        "Party": "उन्‍नत लोकतन्त्र पार्टी",
        "Votes": 184
    }
]